<?xml version='1.0' encoding='UTF-8'?>
<premis xmlns="info:lc/xmlns/premis-v2" xmlns:xsi="http://www.w3.org/2001/XMLSchema-instance" version="2.0" xsi:schemaLocation="info:lc/xmlns/premis-v2 ../../schemas/premis-v2-2.xsd">
  <object xsi:type="representation" xmlID="IDb789bac9-8d94-44b6-baf7-be60cd49dd5f">
    <objectIdentifier>
      <objectIdentifierType>repository</objectIdentifierType>
      <objectIdentifierValue>IDb789bac9-8d94-44b6-baf7-be60cd49dd5f</objectIdentifierValue>
    </objectIdentifier>
  </object>
  <object xsi:type="file" xmlID="IDcfea9f03-83e5-48ad-9a59-4572764d18e7">
    <objectIdentifier>
      <objectIdentifierType>filepath</objectIdentifierType>
      <objectIdentifierValue>file://./data/census/Persons/metadata.xsd</objectIdentifierValue>
    </objectIdentifier>
    <objectCharacteristics>
      <compositionLevel>0</compositionLevel>
      <fixity>
        <messageDigestAlgorithm>SHA-256</messageDigestAlgorithm>
        <messageDigest>87ff46a98cdfc9afa7e93398f29d018dec54713daf2df5a7a8439af4859f7635</messageDigest>
        <messageDigestOriginator>hashlib</messageDigestOriginator>
      </fixity>
      <size>23853</size>
      <format>
        <formatRegistry>
          <formatRegistryName>PRONOM</formatRegistryName>
          <formatRegistryKey>fmt/000</formatRegistryKey>
          <formatRegistryRole>identification</formatRegistryRole>
        </formatRegistry>
      </format>
    </objectCharacteristics>
  </object>
  <object xsi:type="file" xmlID="IDa0636be5-e56c-4542-ad70-20ff083b4483">
    <objectIdentifier>
      <objectIdentifierType>filepath</objectIdentifierType>
      <objectIdentifierValue>file://./data/census/Persons/Persons.xml</objectIdentifierValue>
    </objectIdentifier>
    <objectCharacteristics>
      <compositionLevel>0</compositionLevel>
      <fixity>
        <messageDigestAlgorithm>SHA-256</messageDigestAlgorithm>
        <messageDigest>d17bababe941939e10b1beb535c22545c709b72d6089a122920e526df77ed5ef</messageDigest>
        <messageDigestOriginator>hashlib</messageDigestOriginator>
      </fixity>
      <size>337</size>
      <format>
        <formatRegistry>
          <formatRegistryName>PRONOM</formatRegistryName>
          <formatRegistryKey>fmt/000</formatRegistryKey>
          <formatRegistryRole>identification</formatRegistryRole>
        </formatRegistry>
      </format>
    </objectCharacteristics>
  </object>
  <object xsi:type="file" xmlID="ID7eaee8df-54d0-41da-a654-8b871dd54ce2">
    <objectIdentifier>
      <objectIdentifierType>filepath</objectIdentifierType>
      <objectIdentifierValue>file://./data/census/Persons/Persons.xsd</objectIdentifierValue>
    </objectIdentifier>
    <objectCharacteristics>
      <compositionLevel>0</compositionLevel>
      <fixity>
        <messageDigestAlgorithm>SHA-256</messageDigestAlgorithm>
        <messageDigest>5b3e06324197fe43a984860c21b03a2b42eed9c7ebd44863af7d1eb1ec41d1df</messageDigest>
        <messageDigestOriginator>hashlib</messageDigestOriginator>
      </fixity>
      <size>1350</size>
      <format>
        <formatRegistry>
          <formatRegistryName>PRONOM</formatRegistryName>
          <formatRegistryKey>fmt/000</formatRegistryKey>
          <formatRegistryRole>identification</formatRegistryRole>
        </formatRegistry>
      </format>
    </objectCharacteristics>
  </object>
  <object xsi:type="file" xmlID="IDbaa88f82-b334-40e1-9af9-89a72c711735">
    <objectIdentifier>
      <objectIdentifierType>filepath</objectIdentifierType>
      <objectIdentifierValue>file://./data/census/Persons/metadata.xml</objectIdentifierValue>
    </objectIdentifier>
    <objectCharacteristics>
      <compositionLevel>0</compositionLevel>
      <fixity>
        <messageDigestAlgorithm>SHA-256</messageDigestAlgorithm>
        <messageDigest>7e1abaa506f456343f3d1aaceafd273d245ba5cfb399e5f12d6bb4b376e53d16</messageDigest>
        <messageDigestOriginator>hashlib</messageDigestOriginator>
      </fixity>
      <size>2085</size>
      <format>
        <formatRegistry>
          <formatRegistryName>PRONOM</formatRegistryName>
          <formatRegistryKey>fmt/000</formatRegistryKey>
          <formatRegistryRole>identification</formatRegistryRole>
        </formatRegistry>
      </format>
    </objectCharacteristics>
  </object>
  <agent>
    <agentIdentifier>
      <agentIdentifierType>LOCAL</agentIdentifierType>
      <agentIdentifierValue>Premis Generator</agentIdentifierValue>
    </agentIdentifier>
    <agentName>Premis Generator</agentName>
    <agentType>Software</agentType>
  </agent>
</premis>
