<?xml version='1.0' encoding='UTF-8'?>
<premis xmlns="info:lc/xmlns/premis-v2" xmlns:xsi="http://www.w3.org/2001/XMLSchema-instance" version="2.0" xsi:schemaLocation="info:lc/xmlns/premis-v2 ../../schemas/premis-v2-2.xsd">
  <object xsi:type="representation" xmlID="IDdd18f068-586e-415a-9c74-05f4dd15c8a8">
    <objectIdentifier>
      <objectIdentifierType>repository</objectIdentifierType>
      <objectIdentifierValue>IDdd18f068-586e-415a-9c74-05f4dd15c8a8</objectIdentifierValue>
    </objectIdentifier>
  </object>
  <object xsi:type="file" xmlID="ID5f5c5c0b-d010-461c-9941-91588f63a614">
    <objectIdentifier>
      <objectIdentifierType>filepath</objectIdentifierType>
      <objectIdentifierValue>file://./data/census.sql</objectIdentifierValue>
    </objectIdentifier>
    <objectCharacteristics>
      <compositionLevel>0</compositionLevel>
      <fixity>
        <messageDigestAlgorithm>SHA-256</messageDigestAlgorithm>
        <messageDigest>977fb584d53cd64662dfba427f35190813dfc58979f51a2703f8621b9e1bc274</messageDigest>
        <messageDigestOriginator>hashlib</messageDigestOriginator>
      </fixity>
      <size>2021</size>
      <format>
        <formatRegistry>
          <formatRegistryName>PRONOM</formatRegistryName>
          <formatRegistryKey>fmt/000</formatRegistryKey>
          <formatRegistryRole>identification</formatRegistryRole>
        </formatRegistry>
      </format>
    </objectCharacteristics>
  </object>
  <agent>
    <agentIdentifier>
      <agentIdentifierType>LOCAL</agentIdentifierType>
      <agentIdentifierValue>Premis Generator</agentIdentifierValue>
    </agentIdentifier>
    <agentName>Premis Generator</agentName>
    <agentType>Software</agentType>
  </agent>
</premis>
